databricks/__init__.py
databricks/sdk/__init__.py
databricks/sdk/azure.py
databricks/sdk/casing.py
databricks/sdk/clock.py
databricks/sdk/config.py
databricks/sdk/core.py
databricks/sdk/credentials_provider.py
databricks/sdk/dbutils.py
databricks/sdk/environments.py
databricks/sdk/oauth.py
databricks/sdk/py.typed
databricks/sdk/retries.py
databricks/sdk/version.py
databricks/sdk/_widgets/__init__.py
databricks/sdk/_widgets/default_widgets_utils.py
databricks/sdk/_widgets/ipywidgets_utils.py
databricks/sdk/errors/__init__.py
databricks/sdk/errors/base.py
databricks/sdk/errors/mapper.py
databricks/sdk/errors/platform.py
databricks/sdk/errors/sdk.py
databricks/sdk/mixins/__init__.py
databricks/sdk/mixins/compute.py
databricks/sdk/mixins/files.py
databricks/sdk/mixins/workspace.py
databricks/sdk/runtime/__init__.py
databricks/sdk/runtime/dbutils_stub.py
databricks/sdk/runtime/stub.py
databricks/sdk/service/__init__.py
databricks/sdk/service/_internal.py
databricks/sdk/service/billing.py
databricks/sdk/service/catalog.py
databricks/sdk/service/compute.py
databricks/sdk/service/dashboards.py
databricks/sdk/service/files.py
databricks/sdk/service/iam.py
databricks/sdk/service/jobs.py
databricks/sdk/service/ml.py
databricks/sdk/service/oauth2.py
databricks/sdk/service/pipelines.py
databricks/sdk/service/provisioning.py
databricks/sdk/service/serving.py
databricks/sdk/service/settings.py
databricks/sdk/service/sharing.py
databricks/sdk/service/sql.py
databricks/sdk/service/vectorsearch.py
databricks/sdk/service/workspace.py
databricks_sdk_secure-0.19.0.dist-info/LICENSE
databricks_sdk_secure-0.19.0.dist-info/METADATA
databricks_sdk_secure-0.19.0.dist-info/NOTICE
databricks_sdk_secure-0.19.0.dist-info/WHEEL
databricks_sdk_secure-0.19.0.dist-info/top_level.txt
databricks_sdk_secure-0.19.0.dist-info/RECORD
