Metadata-Version: 2.1
Name: databricks-sdk-secure
Version: 0.19.0
Summary: Databricks SDK for Python (Beta)
Home-page: https://databricks-sdk-py.readthedocs.io
Author: Michael Spece
Author-email: Michael@Spece.AI
Keywords: databricks sdk
Classifier: Development Status :: 4 - Beta
Classifier: Intended Audience :: Developers
Classifier: Intended Audience :: Science/Research
Classifier: Intended Audience :: System Administrators
Classifier: License :: OSI Approved :: Apache Software License
Classifier: Programming Language :: Python :: 3.7
Classifier: Programming Language :: Python :: 3.8
Classifier: Programming Language :: Python :: 3.9
Classifier: Programming Language :: Python :: 3.10
Classifier: Programming Language :: Python :: 3.11
Classifier: Programming Language :: Python :: 3.12
Classifier: Operating System :: OS Independent
Requires-Python: >=3.7
License-File: LICENSE
License-File: NOTICE
Requires-Dist: requests <3,>=2.28.1
Requires-Dist: google-auth ~=2.0
Provides-Extra: dev
Requires-Dist: pytest ; extra == 'dev'
Requires-Dist: pytest-cov ; extra == 'dev'
Requires-Dist: pytest-xdist ; extra == 'dev'
Requires-Dist: pytest-mock ; extra == 'dev'
Requires-Dist: yapf ; extra == 'dev'
Requires-Dist: pycodestyle ; extra == 'dev'
Requires-Dist: autoflake ; extra == 'dev'
Requires-Dist: isort ; extra == 'dev'
Requires-Dist: wheel ; extra == 'dev'
Requires-Dist: ipython ; extra == 'dev'
Requires-Dist: ipywidgets ; extra == 'dev'
Requires-Dist: requests-mock ; extra == 'dev'
Requires-Dist: pyfakefs ; extra == 'dev'
Provides-Extra: notebook
Requires-Dist: ipython <9,>=8 ; extra == 'notebook'
Requires-Dist: ipywidgets <9,>=8 ; extra == 'notebook'
